grapes/__init__.py
grapes/cgraph.cpython-311-darwin.so
grapes/cgraph/__init__.pyi
grapes/cgraph/cgraph.c
grapes/cgraph/cgraph.h
grapes/cgraph/deque.c
grapes/cgraph/deque.h
grapes/cgraph/heap.c
grapes/cgraph/heap.h
grapes/cgraph/macros.h
grapes/cgraph/trav.c
grapes/cgraph/trav.h
grapes/lgraph/__init__.py
grapes/lgraph/colors.py
grapes/lgraph/errors.py
grapes/lgraph/invmap.py
grapes/lgraph/renderer.py
grapes/lgraph/wrapper.py
grapes/lgraph/font/courier-prime-32-126.png
grapes/lgraph/shaders/edge.frag
grapes/lgraph/shaders/edge.geom
grapes/lgraph/shaders/edge.vert
grapes/lgraph/shaders/node.frag
grapes/lgraph/shaders/node.geom
grapes/lgraph/shaders/node.vert
grapes/lgraph/shaders/text.frag
grapes/lgraph/shaders/text.geom
grapes/lgraph/shaders/text.vert
grapes_graph-0.1.1.dist-info/LICENSE.txt
grapes_graph-0.1.1.dist-info/METADATA
grapes_graph-0.1.1.dist-info/WHEEL
grapes_graph-0.1.1.dist-info/top_level.txt
grapes_graph-0.1.1.dist-info/RECORD
