Metadata-Version: 2.1
Name: grapes-graph
Version: 0.1.1
Summary: Python graph library written in C
Author-email: Eric Wang <ericwangyy@ucla.edu>
License: MIT License
Keywords: graph
Classifier: Development Status :: 1 - Planning
Classifier: Programming Language :: C
Classifier: Programming Language :: Python :: 3
Classifier: Programming Language :: Python :: 3.9
Classifier: Programming Language :: Python :: 3.10
Classifier: Programming Language :: Python :: 3.11
Classifier: Programming Language :: Python :: Implementation :: CPython
Requires-Python: >=3.9
License-File: LICENSE.txt
Requires-Dist: moderngl >=5.7.0
Requires-Dist: moderngl-window >=2.4.3
Requires-Dist: numpy >=1.23.2
Requires-Dist: Pillow <10,>=9
Requires-Dist: typing-extensions >=4.6.0
